{"authors": ["Reuters Staff"], "body": "The skyline with its banking district is photographed during sunset in Frankfurt, Germany, April 29, 2020, as the spread of the coronavirus disease (COVID-19) continues. REUTERS/Kai Pfaffenbach\n\nLondon (Reuters) - Deutschland und Frankreich haben in der Europ\u00e4ischen Union nach Reuters-Informationen zu Lockerungen bei Kapital- und Boni-Regeln f\u00fcr Banken aufgerufen.\n\nWie aus einem von Vertretern der Finanzministerin in Berlin und Paris an andere EU-L\u00e4nder gerichteten Dokument hervorgeht, soll so ein Abw\u00fcrgen der Vergabe von Krediten verhindert werden, w\u00e4hrend die Wirtschaft versucht, sich von der Corona-Krise zu erholen. Die Nachrichtenagentur konnte das Papier einsehen.\n\nHintergrund ist die anstehende gesetzliche Verankerung letzter Details strengerer Kapitalvorschriften f\u00fcr Geldh\u00e4user, auf die sich die globalen Bankenregulierer Ende 2017 geeinigt hatten als Konsequenz aus der weltweiten Finanzkrise. Ziel der Reform unter dem Namen \u201cBasel III\u201d ist es, die Bankenbranche stabiler zu machen. So m\u00fcssen die Institute Kredite k\u00fcnftig mit mehr Eigenkapital unterlegen. Wegen der Virus-Pandemie wurde den Banken f\u00fcr die Einf\u00fchrung der sch\u00e4rferen Regeln bereits mehr Zeit gew\u00e4hrt.", "current_date": "2020-09-14 22:44:32.761403", "publish_date": "2020-09-14", "publish_datetime": "2020-09-14 16:15:19+00:00", "publish_time": "16:15:19", "source": "reuters", "title": "Dokument - Berlin und Paris fordern Lockerung von Kapitalregeln f\u00fcr Banken", "topics": ["paris", "der", "mehr", "berlin", "zu", "kapitalregeln", "banken", "ist", "dokument", "die", "f\u00fcr", "von", "lockerung", "sich", "und", "fordern"]}