{"authors": ["Reuters Staff"], "body": "Posts shared more than 13,000 times on Facebook claim The Royal British Legion charity will stop selling poppies to honour military service in parts of the United Kingdom because some minorities have said it upsets them. This is not true.\n\nPoppies are seen in a pile at the British Legion Poppy Factory in Richmond, west London November 1, 2011.\n\nThe posts read: \u201cI\u2019ve just heard some really shocking news, The Royal British Legion are not selling poppies in certain areas on Nov 11 this year. This is because some minorities say that it will upset them, I say sod off ... The poppy is a symbol of reverence for our fallen heroes of all the wars the BRITISH military have fought in. BRITAIN STAND UP AND SAY.........\u2019WE WANT THE POPPY SOLD EVERY WHERE IN THE UK\u2019. THIS SHOULD BE OUR RIGHT. PLEASE RE-POST\u201d.\n\nPosts sharing the false claim can be seen (here , tinyurl.com/y465xwl4 , here) .\n\nThe Poppy Appeal is the charity's biggest fundraising campaign, and is held every year in November during the period of Remembrance (here) .\n\nThe Royal British Legion told Reuters that claims suggesting poppies are not being offered in certain areas of Britain are not true.\n\nThe rumour, the charity says, is one that resurfaces each year (here) .\n\n\u201cWe have always offered the Poppy in every community and area of the United Kingdom and we will continue to do so\u201d, the charity said in a statement.\n\n\u201cThe Poppy is universally respected as the symbol of Remembrance and hope. It is offered to, and worn by, all communities in Britain. The money raised by the Poppy Appeal supports all members of the Armed Forces, veterans, and their families.\u201d\n\nVERDICT\n\nFalse. The Royal British Legion is not stopping the sale of poppies in parts of the UK because of upset minorities. This is an old rumour.\n\nThis article was produced by the Reuters Fact Check team. Read more about our fact-checking work here .", "current_date": "2020-09-14 22:44:49.824011", "publish_date": "2020-09-14", "publish_datetime": "2020-09-14 15:35:32+00:00", "publish_time": "15:35:32", "source": "reuters", "title": "Fact check: False claim around Royal British Legion's sale of poppies circulates again", "topics": ["poppies", "claim", "fact", "sale", "circulates", "royal", "check", "legions", "legion", "offered", "minorities", "british", "britain", "poppy", "upset", "charity", "false"]}