{"authors": ["Reuters Staff"], "body": "INDICE RIC ORE 16,30 VAR. % CHIUS. PREC. FTSE MIB 19.781,85 -0,21 19.820,75 Allshare 21.630,15 -0,23 21.678,23 Banche 7.052,86 -0,09 7.058,97 Oil & Gas 10.341,33 -1,66 10.516,69 Aut & PR 206.342,05 +0,21 205.899,53 Volumi 870 mln MILANO, 14 settembre (Reuters) - Seduta che non decolla a Piazza Affari, e pi\u00f9 in generale sugli altri mercati europei. E anche l'avvio sostenuto di Wall Street non sembra offrire spunti sufficienti agli investitori per entrare sui mercati. \"Il continuo saliscendi degli indici Usa sta scuotendo i mercati e gli stessi investitori non sanno come muoversi\", osserva un trader. In generale, il sentiment \u00e8 comunque sostenuto dalle rinnovate speranze sul fronte del vaccino anti-Covid, alimentate dalla notizia del weekend che il gruppo farmaceutico AstraZeneca ha ripreso la sperimentazione clinica nel Regno Unito dopo che la scorsa settimana i test erano stati interrotti perch\u00e9 un volontario si era sentito male. Sul fronte delle materie prime, il Brent \u00e8 stabile sotto i 40 dollari al barile sempre sui timori legati alla domanda, mentre lo spread del rendimento fra titoli di stato decennali italiani e tedeschi si muove intorno ai 145 punti base. ** Bene l'high tech che a Milano vede STM in progresso del 3,7% circa in un settore rinvigorito anche dalla notizia che Nvidia acquisir\u00e0 il designer di chip Arm dalla giapponese SoftBank per 40 miliardi di dollari, uno dei pi\u00f9 importanti accordi degli ultimi tempi nel mercato dei semiconduttori. ** Nel settore farmaceutico RECORDATI in rialzo dello 0,6% circa. DIASORIN -0,2%. ** Acquisti anche nel settore industriale e automotive con LEONARDO in salita dell'1,2%, FCA a +0,5% e PIRELLI < PIRC.MI> a +0,98%. Scivola CNH in flessione del 3,6%. ** Fra le banche INTESA SANPAOLO e UNICREDIT in linea con l'indice. Strappa INTERMOBILIARE con un balzo del 12% circa. ** Il calo del prezzo del barile zavorra il settore: SAIPEM in flessione dell'1,2%, mentre ENI cede l'1,6% dopo che Credit Suisse ha tagliato il rating a 'underperform' da 'neutral' con un target price ridotto a 9,2 euro. ** Ribassi nel resto degli energetici con ENEL e SNAM in calo tra 0,9% e 1,1%. ** Piatta MEDIASET dopo la recente corsa legata alle speculazioni sulle trattative con Vivendi per porre fine alla battaglia legale che dura da quattro anni. Calo pi\u00f9 marcato per TISCALI in flessione del 12% circa. ** Infine, prosegue il balzo di ACOTEL, in asta di volatilit\u00e0 dopo un ultimo prezzo in rialzo del 14,9%. ** AZIONARIO ITALIANO ** I prezzi delle azioni trattate sul mercato telematica italiano possono essere visualizzati con un doppio click sui seguenti codici ....... Market statistica................................ 20 maggiori rialzi (in percentuale).............. 20 maggiori ribassi (in percentuale)............. Indice FTSE IT Allshare .... 2Indice FTSE Mib .............. Indice FTSE Italia Star ..... Indice FTSE Italia Mid Cap .. Indice FTSE Italia Small Cap . Indice FTSE Italia Micro Cap . Per i prezzi delle azioni trattate sull'Aim .... Guida per azionario Italia.... DERIVATI DI BORSA Futures su FTSE Mib.......... Mini FTSE Mib................. Guida a futures e opzioni.... Guida a opzioni.............. ** BORSE EUROPEE ** Commento su titoli europei ...... Commento in italiano su borse europee Speed guide borse europee......... Indici pan europei ............. Dati analitici paneuropei........ Indice FTSEurofirst 300.......... Indice Stoxx..................... Indice Eurostoxx................. Maggiori rialzi/ribassi settori Stoxx ........ Maggiori rialzi/ribassi settori Eurostoxx..... 10 maggiori rialzi/ribassi titoli Stoxx....... 10 maggiori rialzi/ribassi titoli Euro Stoxx.. 25 maggiori rialzi europei......... 25 maggiori ribassi europei........ 25 titoli pi\u00f9 attivi in valore .... Guida a informazioni Reuters ...... Guida a azionario ................. Chain degli indici italiani........ (Giancarlo Navach, in redazione a Milano Sabina Suzzi)", "current_date": "2020-09-14 22:44:49.735323", "publish_date": "2020-09-14", "publish_datetime": "2020-09-14 14:40:04+00:00", "publish_time": "14:40:04", "source": "reuters", "title": "BORSA MILANO poco mossa, volumi scarsi, corre Stm, gi\u00f9 Tiscali", "topics": ["stm", "gi\u00f9", "titoli", "milano", "italia", "poco", "mossa", "del", "volumi", "scarsi", "che", "maggiori", "nel", "il", "tiscali", "borsa", "corre", "indice", "di", "ftse"]}