{"authors": ["Reuters Staff"], "body": "\"Bear\" y su adiestradora, Romane Cristescu, fundadora de Detection Dogs y ecologista de la Universidad de Sunshine Coast en Kandanga, Australia. 16 de enero de 2020. USC Detection Dogs For Conservation/Handout via REUTERS\n\nS\u00cdDNEY, 14 sep (Reuters) - Un grupo de cient\u00edficos de Australia est\u00e1 utilizando perros rastreadores para rescatar a los koalas amenazados por los incendios forestales que asolan el pa\u00eds, en un intento por evitar que se repita el alto n\u00famero de muertes de estos animales registrado el a\u00f1o pasado.\n\nLiderados por Bear, un cruce de border collie y boyero australiano, los perros rastreadores salvaron a m\u00e1s de 100 koalas en el peor verano de incendios vivido en el pa\u00eds en d\u00e9cadas, entre finales de 2019 y principios de 2020. Cerca de 6.000 koalas murieron y miles de hect\u00e1reas de su h\u00e1bitat natural fueron pasto de las llamas.\n\nCasi exactamente un a\u00f1o despu\u00e9s desde que comenzaran los primeros incendios de esa fat\u00eddica temporada, Bear (Oso, en ingl\u00e9s) ha vuelto a la acci\u00f3n en el estado de Queensland.\n\n\u201cAunque es poco probable que veamos incendios forestales de la magnitud de los del a\u00f1o pasado, todav\u00eda nos estamos preparando para m\u00faltiples incendios que pueden afectar a muchas hect\u00e1reas del h\u00e1bitat de los koalas durante la pr\u00f3xima temporada\u201d, dijo la fundadora de Detection Dogs, Romane Cristescu, ecologista de la Universidad de Sunshine Coast.\n\n\u201cEn lugares como Queensland y Nueva Gales del Sur, donde las poblaciones ya est\u00e1n disminuyendo, cada koala cuenta\u201d, a\u00f1adi\u00f3.\n\nLos incendios arrasaron m\u00e1s de 11 millones de hect\u00e1reas de matorral en todo el sureste de Australia, en lo que el primer ministro Scott Morrison llam\u00f3 un \u201cverano negro\u201d para el pa\u00eds, durante el cual murieron al menos 33 personas y miles de millones de fauna local.\n\nLa Agencia Meteorol\u00f3gica australiana espera una primavera m\u00e1s fresca y lluviosa para la mayor parte del pa\u00eds, aunque los estados del norte del pa\u00eds como Queensland pueden experimentar temperaturas superiores a la media.", "current_date": "2020-09-14 22:44:17.578204", "publish_date": "2020-09-14", "publish_datetime": "2020-09-14 10:54:28+00:00", "publish_time": "10:54:28", "source": "reuters", "title": "Un equipo de perros lidera la lucha para salvar del fuego a los koalas australianos", "topics": ["fuego", "que", "equipo", "lucha", "pa\u00eds", "salvar", "y", "incendios", "los", "para", "el", "del", "koalas", "lidera", "perros", "la", "en"]}